aloni/__init__.py
aloni/application_mode.py
aloni/application_run_result.py
aloni/application_state.py
aloni/asset/application_asset_registry.py
aloni/asset/asset.py
aloni/cli/__init__.py
aloni/cli/check.py
aloni/cli/format.py
aloni/cli/serve.py
aloni/cli_foundation/__init__.py
aloni/cli_foundation/command.py
aloni/cli_foundation/command_option.py
aloni/dependency_injection_container.py
aloni/http/__init__.py
aloni/http/asset_response.py
aloni/http/asset_response_interceptor.py
aloni/http/exception_responder.py
aloni/http/exception_response.py
aloni/http/internal_link_builder.py
aloni/http/jinja_response.py
aloni/http/jinja_response_interceptor.py
aloni/http/not_found_responder.py
aloni/http/not_found_response.py
aloni/http/recursive_responder_aggregate.py
aloni/http/request_context.py
aloni/http/responder.py
aloni/http/responder_caller.py
aloni/http/response_interceptor.py
aloni/http/response_interceptor_aggregate.py
aloni/http/route.py
aloni/http/route_dynamic_matcher.py
aloni/http/route_dynamic_node.py
aloni/http/route_dynamic_node_match.py
aloni/http/route_match.py
aloni/http/route_pattern.py
aloni/http/router.py
aloni/http/text_response.py
aloni/http_foundation/__init__.py
aloni/http_foundation/file_response.py
aloni/http_foundation/final_response.py
aloni/http_foundation/renderable_response.py
aloni/http_foundation/request.py
aloni/http_foundation/response.py
aloni/import_all_from.py
aloni/jinja_function/__init__.py
aloni/jinja_function/jinja_function.py
aloni/jinja_function/url_for.py
aloni/meta/__init__.py
aloni/meta/argument_matching_function_caller.py
aloni/meta/async_responder_protocol.py
aloni/meta/class_property_info.py
aloni/meta/function_parameter.py
aloni/meta/function_parameter_store.py
aloni/meta/get_class_properties.py
aloni/meta/get_full_class_name.py
aloni/meta/get_root_class.py
aloni/meta/is_responder.py
aloni/meta/responder_protocol.py
aloni/meta/test_argument_matching_function_caller.py
aloni/py.typed
aloni/role/__init__.py
aloni-0.2.3.dist-info/LICENSE.md
aloni-0.2.3.dist-info/METADATA
aloni-0.2.3.dist-info/WHEEL
aloni-0.2.3.dist-info/RECORD
