Metadata-Version: 2.1
Name: aloni
Version: 0.2.3
Summary: 
Author: Mateusz Charytoniuk
Author-email: mateusz.charytoniuk@protonmail.com
Requires-Python: >=3.11,<4.0
Classifier: Programming Language :: Python :: 3
Classifier: Programming Language :: Python :: 3.11
Classifier: Programming Language :: Python :: 3.12
Requires-Dist: dill (>=0.3.8,<0.4.0)
Requires-Dist: granian (>=1.4.3,<2.0.0)
Requires-Dist: jinja2 (>=3.1.4,<4.0.0)
Requires-Dist: mypy (>=1.10.0,<2.0.0)
Requires-Dist: natsort (>=8.4.0,<9.0.0)
Requires-Dist: ruff (>=0.4.9,<0.5.0)
Requires-Dist: typeguard (>=4.3.0,<5.0.0)
